README.md
setup.cfg
setup.py
vdhost/__init__.py
vdhost/main.py
vdhost.egg-info/PKG-INFO
vdhost.egg-info/SOURCES.txt
vdhost.egg-info/dependency_links.txt
vdhost.egg-info/entry_points.txt
vdhost.egg-info/not-zip-safe
vdhost.egg-info/requires.txt
vdhost.egg-info/top_level.txt
vdhost/cli/__init__.py
vdhost/cli/commands.py
vdhost/cli/decorators.py
vdhost/cli/env.py