Metadata-Version: 1.0
Name: vdhost
Version: 2.1.21
Summary: Command line interface for Vectordash hosts.
Home-page: https://github.com/Vectordash/vectordash-host
Author: Arbaz
Author-email: contact@vectordash.com
License: UNKNOWN
Keywords: vectordash
Platform: UNKNOWN
